efmtool_link/__init__.py
efmtool_link/efmtool4cobra.py
efmtool_link/efmtool_extern.py
efmtool_link/efmtool_intern.py
efmtool_link/lib/applib.jar
efmtool_link/lib/commons-logging-1.0.1.jar
efmtool_link/lib/dom4j-1.6.1.jar
efmtool_link/lib/efm-prepareout.jar
efmtool_link/lib/jaxen-1.1-beta-10.jar
efmtool_link/lib/junit-3.8.1.jar
efmtool_link/lib/log4j-1.2.8.jar
efmtool_link/lib/metabolic-efm-all.jar
efmtool_link/lib/mtj.jar
efmtool_link/lib/poi-3.1-FINAL-20080629.jar
efmtool_link-0.0.7.dist-info/LICENSE
efmtool_link-0.0.7.dist-info/METADATA
efmtool_link-0.0.7.dist-info/WHEEL
efmtool_link-0.0.7.dist-info/top_level.txt
efmtool_link-0.0.7.dist-info/RECORD
