Metadata-Version: 2.1
Name: efmtool_link
Version: 0.0.7
Summary: Exposes various efmtool functionality in Python.
Author-email: Axel von Kamp <vonkamp@mpi-magdeburg.mpg.de>
Project-URL: Homepage, https://github.com/cnapy-org/efmtool_link
Project-URL: Issues, https://github.com/cnapy-org/efmtool_link/issues
Classifier: Programming Language :: Python :: 3
Classifier: License :: OSI Approved :: Apache Software License
Classifier: Operating System :: OS Independent
Requires-Python: >=3.7
License-File: LICENSE
Requires-Dist: jpype1
Requires-Dist: numpy
Requires-Dist: scipy
Requires-Dist: cobra
Requires-Dist: psutil
